pygments_bsl/__init__.py
pygments_bsl/generated_data.py
pygments_bsl/lexer.py
pygments_bsl-1.0.1.dist-info/licenses/LICENSE
tests/__init__.py
tests/test_lexer.py
pygments_bsl-1.0.1.dist-info/METADATA
pygments_bsl-1.0.1.dist-info/WHEEL
pygments_bsl-1.0.1.dist-info/entry_points.txt
pygments_bsl-1.0.1.dist-info/top_level.txt
pygments_bsl-1.0.1.dist-info/RECORD
