Metadata-Version: 2.4
Name: pygments-bsl
Version: 1.0.1
Summary: Pygments 1C (BSL, SDBL) lexer
Home-page: https://github.com/zeegin/pygments-bsl
Author: Ingvar Vilkman
Author-email: zeegin@zeegin.com
License: MIT License
Classifier: Environment :: Plugins
Classifier: Intended Audience :: Developers
Classifier: License :: OSI Approved :: MIT License
Classifier: Operating System :: OS Independent
Classifier: Programming Language :: Python :: 3
License-File: LICENSE
Requires-Dist: pygments>=2.3
Dynamic: author
Dynamic: author-email
Dynamic: classifier
Dynamic: description
Dynamic: description-content-type
Dynamic: home-page
Dynamic: license
Dynamic: license-file
Dynamic: requires-dist
Dynamic: summary
